setup.py
jz/__init__.py
jz.common.egg-info/PKG-INFO
jz.common.egg-info/SOURCES.txt
jz.common.egg-info/dependency_links.txt
jz.common.egg-info/namespace_packages.txt
jz.common.egg-info/requires.txt
jz.common.egg-info/top_level.txt
jz/common/__init__.py
jz/common/author.txt
jz/common/configure.zcml
jz/common/jz.common-configure.zcml
jz/common/readme.txt
jz/common/startup/__init__.py
jz/common/startup/configure.zcml
jz/common/tests/__init__.py
jz/common/tests/test_common.py
