Metadata-Version: 1.0
Name: jz.common
Version: 0.1
Summary: Common objects for jz package collection.
Home-page: http://www.jellofishi.com/zope
Author: Gabi Shaar
Author-email: gabi@jbox-comp.com
License: GPL
Platform: UNKNOWN
